WordyAPI/WordyAPI.py
WordyAPI/__init__.py
WordyAPI-1.0.1.dist-info/METADATA
WordyAPI-1.0.1.dist-info/WHEEL
WordyAPI-1.0.1.dist-info/top_level.txt
WordyAPI-1.0.1.dist-info/RECORD
