Metadata-Version: 2.1
Name: WordyAPI
Version: 1.0.1
Summary: Wordy is a unique NLP system that provides great imitation writing examples for Chinese texts. Unlike other text generators, this system will not change the original discourse structure of the text. 
Home-page: https://github.com/Droidtown/WordyAPI
Author: Droidtown Linguistic Tech. Co. Ltd.
Author-email: info@droidtown.co
License: MIT License
Project-URL: Documentation, https://api.droidtown.co/document/#Wordy
Project-URL: Source, https://github.com/Droidtown/WordyAPI
Keywords: NLP,NLU,AI,artificial intelligence,computational linguistics,language,linguistics,natural language,natural language processing,natural language understanding,text analytics,imitation writing
Platform: UNKNOWN
Classifier: Programming Language :: Python :: 3
Classifier: Programming Language :: Python :: 3 :: Only
Classifier: Programming Language :: Python :: 3.6
Classifier: Programming Language :: Python :: 3.7
Classifier: Programming Language :: Python :: 3.8
Classifier: Programming Language :: Python :: 3.9
Classifier: License :: OSI Approved :: MIT License
Classifier: Operating System :: OS Independent
Classifier: Development Status :: 5 - Production/Stable
Classifier: Intended Audience :: Developers
Classifier: Intended Audience :: Customer Service
Classifier: Intended Audience :: Information Technology
Classifier: Natural Language :: Chinese (Traditional)
Classifier: Topic :: Software Development :: Libraries :: Python Modules
Classifier: Topic :: Text Processing
Classifier: Topic :: Text Processing :: Linguistic
Classifier: Topic :: Text Processing :: Filters
Classifier: Topic :: Utilities
Requires-Python: >=3.6.1
Requires-Dist: requests (>=2.25.1)
